{"name":"javadoc","path":"graphlib/1.0.0-beta.3+1.20/javadoc","children":[{"name":"allclasses-index.html","path":"graphlib/1.0.0-beta.3+1.20/javadoc/allclasses-index.html","type":"file","size":47637},{"name":"allpackages-index.html","path":"graphlib/1.0.0-beta.3+1.20/javadoc/allpackages-index.html","type":"file","size":4882},{"name":"com","path":"graphlib/1.0.0-beta.3+1.20/javadoc/com","type":"directory"},{"name":"deprecated-list.html","path":"graphlib/1.0.0-beta.3+1.20/javadoc/deprecated-list.html","type":"file","size":3492},{"name":"element-list","path":"graphlib/1.0.0-beta.3+1.20/javadoc/element-list","type":"file","size":374},{"name":"help-doc.html","path":"graphlib/1.0.0-beta.3+1.20/javadoc/help-doc.html","type":"file","size":8968},{"name":"index-all.html","path":"graphlib/1.0.0-beta.3+1.20/javadoc/index-all.html","type":"file","size":318313},{"name":"index.html","path":"graphlib/1.0.0-beta.3+1.20/javadoc/index.html","type":"file","size":5825},{"name":"jquery-ui.overrides.css","path":"graphlib/1.0.0-beta.3+1.20/javadoc/jquery-ui.overrides.css","type":"file","size":1498},{"name":"legal","path":"graphlib/1.0.0-beta.3+1.20/javadoc/legal","type":"directory"},{"name":"member-search-index.js","path":"graphlib/1.0.0-beta.3+1.20/javadoc/member-search-index.js","type":"file","size":82300},{"name":"module-search-index.js","path":"graphlib/1.0.0-beta.3+1.20/javadoc/module-search-index.js","type":"file","size":45},{"name":"overview-summary.html","path":"graphlib/1.0.0-beta.3+1.20/javadoc/overview-summary.html","type":"file","size":839},{"name":"overview-tree.html","path":"graphlib/1.0.0-beta.3+1.20/javadoc/overview-tree.html","type":"file","size":30898},{"name":"package-search-index.js","path":"graphlib/1.0.0-beta.3+1.20/javadoc/package-search-index.js","type":"file","size":557},{"name":"resources","path":"graphlib/1.0.0-beta.3+1.20/javadoc/resources","type":"directory"},{"name":"script-dir","path":"graphlib/1.0.0-beta.3+1.20/javadoc/script-dir","type":"directory"},{"name":"script.js","path":"graphlib/1.0.0-beta.3+1.20/javadoc/script.js","type":"file","size":5027},{"name":"search.js","path":"graphlib/1.0.0-beta.3+1.20/javadoc/search.js","type":"file","size":13759},{"name":"stylesheet.css","path":"graphlib/1.0.0-beta.3+1.20/javadoc/stylesheet.css","type":"file","size":18737},{"name":"tag-search-index.js","path":"graphlib/1.0.0-beta.3+1.20/javadoc/tag-search-index.js","type":"file","size":42},{"name":"type-search-index.js","path":"graphlib/1.0.0-beta.3+1.20/javadoc/type-search-index.js","type":"file","size":6038}]}